certbot_dns_mydnsjp/__init__.py
certbot_dns_mydnsjp/cert/__init__.py
certbot_dns_mydnsjp/cert/client.py
certbot_dns_mydnsjp/mydnsjp/__init__.py
certbot_dns_mydnsjp/mydnsjp/client.py
certbot_dns_mydnsjp-1.0.2.dist-info/LICENSE
certbot_dns_mydnsjp-1.0.2.dist-info/METADATA
certbot_dns_mydnsjp-1.0.2.dist-info/WHEEL
certbot_dns_mydnsjp-1.0.2.dist-info/entry_points.txt
certbot_dns_mydnsjp-1.0.2.dist-info/top_level.txt
certbot_dns_mydnsjp-1.0.2.dist-info/RECORD
