Metadata-Version: 2.1
Name: certbot_dns_mydnsjp
Version: 1.0.2
Summary: Authenticator plugin for certbot to handle dns-01 challenge with MyDNS.JP.
Home-page: https://github.com/usk-johnny-s/certbot_dns_mydnsjp/
Author: usk-johnny-s
License: MIT
Classifier: Development Status :: 5 - Production/Stable
Classifier: Programming Language :: Python :: 3
Classifier: Programming Language :: Python :: 3.8
Classifier: Programming Language :: Python :: 3.9
Classifier: Programming Language :: Python :: 3.10
Classifier: Programming Language :: Python :: 3.11
Classifier: Programming Language :: Python :: 3.12
Classifier: License :: OSI Approved :: MIT License
Classifier: Topic :: Security
Classifier: Topic :: Internet :: WWW/HTTP
Classifier: Topic :: Utilities
Classifier: Topic :: System :: Systems Administration
Requires-Python: >=3.8
License-File: LICENSE
Requires-Dist: certbot <3.0,>=1.18.0
Requires-Dist: requests <3.0,>=2.20.0
